my_package.py
package_xinzhu-0.0.1.dist-info/METADATA
package_xinzhu-0.0.1.dist-info/WHEEL
package_xinzhu-0.0.1.dist-info/top_level.txt
package_xinzhu-0.0.1.dist-info/RECORD
