Metadata-Version: 2.1
Name: package-xinzhu
Version: 0.0.1
Summary: A  module for add
Home-page: https://github.com/xinzhu-email/Pantheon
Author: xinzhu
Author-email: xinzhu.jiang@sjtu.edu.cn
License: MIT
